Metadata-Version: 1.0
Name: projhelper
Version: 0.1.8
Summary: project base helper, include logger 
Home-page: UNKNOWN
Author: oujh
Author-email: ojhtyy@163.com
License: MIT Licence
Keywords: pip,datacanvas,helper,proj
Platform: any
